[
  {
    "id": 124,
    "name": "Al-Nassr",
    "league_id": 17,
    "logo": "img/equipos/Al-Nassr FC.png",
    "slug": "al-nassr",
    "sofifa_url": "https://sofifa.com/squad/2233485",
    "tactics_video_url": "",
    "faces_video_url": "",
    "founded_year": "1955",
    "stadium": "Al -Awwal Park",
    "capacity": "25,000",
    "city": "Riad",
    "nickname": "Faris Najd",
    "members": "Desconocido"
  },
  {
    "id": 57,
    "name": "Alavés",
    "league_id": 5,
    "logo": "img/equipos/Deportivo Alavés.png",
    "slug": "deportivo-alaves",
    "sofifa_url": "https://sofifa.com/squad/2289929",
    "tactics_video_url": "",
    "faces_video_url": "",
    "founded_year": "1921",
    "stadium": "Mendizorrotza",
    "capacity": "19.840",
    "city": "Vitoria-Gasteiz",
    "nickname": "El Glorioso",
    "members": "Desconocido"
  },
  {
    "id": 29,
    "name": "Aldosivi",
    "league_id": 1,
    "logo": "img/equipos/Club Atletico Aldosivi.png",
    "slug": "aldosivi",
    "sofifa_url": "https://sofifa.com/squad/2216493",
    "tactics_video_url": "",
    "faces_video_url": "",
    "founded_year": "1913",
    "stadium": "José María Minella",
    "capacity": "35.300",
    "city": "Buenos Aires",
    "nickname": "Tiburón",
    "members": "15.000"
  },
  {
    "id": 116,
    "name": "Alianza Lima",
    "league_id": 14,
    "logo": "img/equipos/Alianza Lima.png",
    "slug": "alianza-lima",
    "sofifa_url": "",
    "tactics_video_url": "",
    "faces_video_url": "",
    "founded_year": "1901",
    "stadium": "Estadio Alejandro Villanueva",
    "capacity": "35.084",
    "city": "Lima",
    "nickname": "Blanquiazules",
    "members": "Desconocido"
  },
  {
    "id": 105,
    "name": "América de Cali",
    "league_id": 11,
    "logo": "img/equipos/America de Cali.png",
    "slug": "america-de-cali",
    "sofifa_url": "https://sofifa.com/squad/2241849",
    "tactics_video_url": "",
    "faces_video_url": "",
    "founded_year": "1927",
    "stadium": "Estadio Olímpico Pascual Guerrero",
    "capacity": "35.405",
    "city": "Cali",
    "nickname": "Los Diablos Rojos",
    "members": "Desconocido"
  },
  {
    "id": 19,
    "name": "Argentinos Juniors",
    "league_id": 1,
    "logo": "img/equipos/Argentinos Juniors.png",
    "slug": "argentinos-juniors",
    "sofifa_url": "https://sofifa.com/squad/2211948",
    "tactics_video_url": "",
    "faces_video_url": "",
    "founded_year": "1904",
    "stadium": "Diego Armando Maradona",
    "capacity": "26.000",
    "city": "Buenos Aires",
    "nickname": "Bicho",
    "members": "36.500"
  },
  {
    "id": 31,
    "name": "Arsenal",
    "league_id": 2,
    "logo": "img/equipos/Arsenal.png",
    "slug": "arsenal",
    "sofifa_url": "https://sofifa.com/squad/2223652",
    "tactics_video_url": "",
    "faces_video_url": "",
    "founded_year": "1886",
    "stadium": "Emirates Stadium",
    "capacity": "60.704",
    "city": "Londres",
    "nickname": "Gunners",
    "members": "Desconocido"
  },
  {
    "id": 32,
    "name": "Aston Villa",
    "league_id": 2,
    "logo": "img/equipos/Aston Villa.png",
    "slug": "aston-villa",
    "sofifa_url": "https://sofifa.com/squad/2271177",
    "tactics_video_url": "",
    "faces_video_url": "",
    "founded_year": "1874",
    "stadium": "Villa Park",
    "capacity": "42.682",
    "city": "Birmingham",
    "nickname": "Villans",
    "members": "Desconocido"
  },
  {
    "id": 125,
    "name": "Atalanta",
    "league_id": 4,
    "logo": "img/equipos/Atalanta Bergamasca Calcio.png",
    "slug": "atalanta",
    "sofifa_url": "https://sofifa.com/squad/2339368",
    "tactics_video_url": "",
    "faces_video_url": "",
    "founded_year": "1907",
    "stadium": "Gewiss Stadium",
    "capacity": "24.000",
    "city": "Bérgamo",
    "nickname": "La Dea",
    "members": "Desconocido"
  },
  {
    "id": 58,
    "name": "Athletic Club",
    "league_id": 5,
    "logo": "img/equipos/Athletic Club.png",
    "slug": "athletic-club",
    "sofifa_url": "https://sofifa.com/squad/2286711",
    "tactics_video_url": "",
    "faces_video_url": "",
    "founded_year": "1898",
    "stadium": "San Mamés",
    "capacity": "53.289",
    "city": "Bilbao",
    "nickname": "Los Leones",
    "members": "Desconocido"
  },
  {
    "id": 106,
    "name": "Atlético Bucaramanga",
    "league_id": 11,
    "logo": "img/equipos/CA Bucaramanga.png",
    "slug": "atletico-bucaramanga",
    "sofifa_url": "https://sofifa.com/squad/2242004",
    "tactics_video_url": "",
    "faces_video_url": "",
    "founded_year": "1949",
    "stadium": "Estadio Alfonso López",
    "capacity": "25.000",
    "city": "Bucaramanga",
    "nickname": "Leopardos",
    "members": "Desconocido"
  },
  {
    "id": 59,
    "name": "Atlético de Madrid",
    "league_id": 5,
    "logo": "img/equipos/Atlético de Madrid.png",
    "slug": "atletico-de-madrid",
    "sofifa_url": "https://sofifa.com/squad/2217322",
    "tactics_video_url": "",
    "faces_video_url": "",
    "founded_year": "1903",
    "stadium": "Cívitas Metropolitano",
    "capacity": "70.460",
    "city": "Madrid",
    "nickname": "Los Colchoneros",
    "members": "Desconocido"
  },
  {
    "id": 80,
    "name": "Atlético Mineiro",
    "league_id": 7,
    "logo": "img/equipos/Atlético-MG.png",
    "slug": "atletico-mg",
    "sofifa_url": "https://sofifa.com/squad/2306918",
    "tactics_video_url": "",
    "faces_video_url": "",
    "founded_year": "1908",
    "stadium": "Arena MRV",
    "capacity": "46.000",
    "city": "Belo Horizonte",
    "nickname": "Galo",
    "members": "106.452 (ago 2025)"
  },
  {
    "id": 107,
    "name": "Atlético Nacional",
    "league_id": 11,
    "logo": "img/equipos/Club Atletico Nacional.png",
    "slug": "atletico-nacional",
    "sofifa_url": "https://sofifa.com/squad/2237670",
    "tactics_video_url": "",
    "faces_video_url": "",
    "founded_year": "1947",
    "stadium": "Estadio Atanasio Girardot",
    "capacity": "45.000",
    "city": "Medellín",
    "nickname": "Rey de Copas",
    "members": "Desconocido"
  },
  {
    "id": 20,
    "name": "Atlético Tucumán",
    "league_id": 1,
    "logo": "img/equipos/Club Atletico Tucuman.png",
    "slug": "atletico-tucuman",
    "sofifa_url": "https://sofifa.com/squad/2213261",
    "tactics_video_url": "",
    "faces_video_url": "",
    "founded_year": "1902",
    "stadium": "Monumental José Fierro",
    "capacity": "35.200",
    "city": "Tucumán",
    "nickname": "Decano",
    "members": "35.000"
  },
  {
    "id": 81,
    "name": "Bahia",
    "league_id": 7,
    "logo": "img/equipos/Bahia.png",
    "slug": "bahia",
    "sofifa_url": "https://sofifa.com/squad/2306916",
    "tactics_video_url": "",
    "faces_video_url": "",
    "founded_year": "1931",
    "stadium": "Arena Fonte Nova",
    "capacity": "50.025",
    "city": "Salvador",
    "nickname": "Esquadrão de Aço",
    "members": "77.000 (jun 2025)"
  },
  {
    "id": 21,
    "name": "Banfield",
    "league_id": 1,
    "logo": "img/equipos/Club Atletico Banfield.png",
    "slug": "banfield",
    "sofifa_url": "https://sofifa.com/squad/2212753",
    "tactics_video_url": "",
    "faces_video_url": "",
    "founded_year": "1896",
    "stadium": "Florencio Sola",
    "capacity": "34.901",
    "city": "Buenos Aires",
    "nickname": "Taladro",
    "members": "27.000"
  },
  {
    "id": 60,
    "name": "Barcelona",
    "league_id": 5,
    "logo": "img/equipos/F.C. Barcelona.png",
    "slug": "fc-barcelona",
    "sofifa_url": "https://sofifa.com/squad/2215522",
    "tactics_video_url": "https://youtu.be/l_iZ0wlV7wc?si=p8ESzSZ7xwtSm0pH",
    "faces_video_url": "",
    "founded_year": "1899",
    "stadium": "Estadio Olímpico Lluís Companys*",
    "capacity": "55.926",
    "city": "Barcelona",
    "nickname": "El Barça",
    "members": "Desconocido"
  },
  {
    "id": 110,
    "name": "Barcelona SC",
    "league_id": 12,
    "logo": "img/equipos/Barcelona SC.png",
    "slug": "barcelona-sc",
    "sofifa_url": "",
    "tactics_video_url": "",
    "faces_video_url": "",
    "founded_year": "1925",
    "stadium": "Estadio Monumental Isidro Romero Carbo",
    "capacity": "57.267",
    "city": "Guayaquil",
    "nickname": "Toreros",
    "members": "Desconocido"
  },
  {
    "id": 26,
    "name": "Barracas Central",
    "league_id": 1,
    "logo": "img/equipos/CA Barracas Central.png",
    "slug": "barracas-central",
    "sofifa_url": "https://sofifa.com/squad/2212785",
    "tactics_video_url": "",
    "faces_video_url": "",
    "founded_year": "1904",
    "stadium": "Claudio Chiqui Tapia",
    "capacity": "4.400",
    "city": "Buenos Aires",
    "nickname": "Guapo",
    "members": "1.500"
  },
  {
    "id": 77,
    "name": "Bayer 04 Leverkusen",
    "league_id": 6,
    "logo": "img/equipos/Bayer 04 Leverkusen.png",
    "slug": "bayer-04-leverkusen",
    "sofifa_url": "https://sofifa.com/squad/2228088",
    "tactics_video_url": "",
    "faces_video_url": "",
    "founded_year": "1904",
    "stadium": "BayArena",
    "capacity": "30.210",
    "city": "Leverkusen",
    "nickname": "Die Werkself",
    "members": "70.000"
  },
  {
    "id": 79,
    "name": "Bayern München",
    "league_id": 6,
    "logo": "img/equipos/FC Bayern Munchen.png",
    "slug": "bayern-munchen",
    "sofifa_url": "https://sofifa.com/squad/2223432",
    "tactics_video_url": "",
    "faces_video_url": "",
    "founded_year": "1900",
    "stadium": "Allianz Arena",
    "capacity": "75.024",
    "city": "Múnich",
    "nickname": "Die Roten",
    "members": "432.500"
  },
  {
    "id": 9,
    "name": "Belgrano",
    "league_id": 1,
    "logo": "img/equipos/Club Atletico Belgrano.png",
    "slug": "belgrano",
    "sofifa_url": "https://sofifa.com/squad/2211983",
    "tactics_video_url": "",
    "faces_video_url": "",
    "founded_year": "1905",
    "stadium": "Gigante de Alberdi",
    "capacity": "33.000",
    "city": "Córdoba",
    "nickname": "Pirata",
    "members": "65.139"
  },
  {
    "id": 2,
    "name": "Boca Juniors",
    "league_id": 1,
    "logo": "img/equipos/Boca Juniors.png",
    "slug": "boca-juniors",
    "sofifa_url": "https://sofifa.com/squad/2211126",
    "tactics_video_url": "None",
    "faces_video_url": "None",
    "founded_year": "1905",
    "stadium": "La Bombonera",
    "capacity": "57.200",
    "city": "Buenos Aires",
    "nickname": "Xeneizes",
    "members": "323.586"
  },
  {
    "id": 126,
    "name": "Bologna",
    "league_id": 4,
    "logo": "img/equipos/Bologna FC.png",
    "slug": "bologna",
    "sofifa_url": "https://sofifa.com/squad/2373684",
    "tactics_video_url": "",
    "faces_video_url": "",
    "founded_year": "1909",
    "stadium": "Renato Dall'Ara",
    "capacity": "36.462",
    "city": "Bolonia",
    "nickname": "Rossoblù",
    "members": "Desconocido"
  },
  {
    "id": 103,
    "name": "Bolívar",
    "league_id": 10,
    "logo": "img/equipos/Club Bolivar.png",
    "slug": "bolivar",
    "sofifa_url": "https://sofifa.com/squad/2218561",
    "tactics_video_url": "",
    "faces_video_url": "",
    "founded_year": "1925",
    "stadium": "Estadio Hernando Siles",
    "capacity": "41.143",
    "city": "La Paz",
    "nickname": "La Academia Celeste",
    "members": "Desconocido"
  },
  {
    "id": 78,
    "name": "Borussia Dortmund",
    "league_id": 6,
    "logo": "img/equipos/Borussia Dortmund.png",
    "slug": "borussia-dortmund",
    "sofifa_url": "https://sofifa.com/squad/2228100",
    "tactics_video_url": "",
    "faces_video_url": "",
    "founded_year": "1909",
    "stadium": "Signal Iduna Park",
    "capacity": "81.365",
    "city": "Dortmund",
    "nickname": "Die Schwarzgelben",
    "members": "230.000"
  },
  {
    "id": 82,
    "name": "Botafogo",
    "league_id": 7,
    "logo": "img/equipos/Botafogo.png",
    "slug": "botafogo",
    "sofifa_url": "https://sofifa.com/squad/2306913",
    "tactics_video_url": "",
    "faces_video_url": "",
    "founded_year": "1894",
    "stadium": "Estádio Nilton Santos",
    "capacity": "46.831",
    "city": "Río de Janeiro",
    "nickname": "Alvinegro",
    "members": "67.000+ (sep 2024)"
  },
  {
    "id": 33,
    "name": "Bournemouth",
    "league_id": 2,
    "logo": "img/equipos/Bournemouth.png",
    "slug": "bournemouth",
    "sofifa_url": "https://sofifa.com/squad/2266683",
    "tactics_video_url": "",
    "faces_video_url": "",
    "founded_year": "1899",
    "stadium": "Vitality Stadium",
    "capacity": "11.379",
    "city": "Bournemouth",
    "nickname": "Cherries",
    "members": "Desconocido"
  },
  {
    "id": 34,
    "name": "Brentford",
    "league_id": 2,
    "logo": "img/equipos/Brentford.png",
    "slug": "brentford",
    "sofifa_url": "https://sofifa.com/squad/2270961",
    "tactics_video_url": "",
    "faces_video_url": "",
    "founded_year": "1889",
    "stadium": "Gtech Community Stadium",
    "capacity": "17.250",
    "city": "Londres",
    "nickname": "Bees",
    "members": "Desconocido"
  },
  {
    "id": 35,
    "name": "Brighton & Hove Albion",
    "league_id": 2,
    "logo": "img/equipos/Brighton & Hove Albion.png",
    "slug": "brighton-hove-albion",
    "sofifa_url": "https://sofifa.com/squad/2270285",
    "tactics_video_url": "",
    "faces_video_url": "",
    "founded_year": "1901",
    "stadium": "American Express Stadium",
    "capacity": "31.876",
    "city": "Brighton",
    "nickname": "Seagulls",
    "members": "Desconocido"
  },
  {
    "id": 36,
    "name": "Burnley",
    "league_id": 2,
    "logo": "img/equipos/Burnley.png",
    "slug": "burnley",
    "sofifa_url": "https://sofifa.com/squad/2271205",
    "tactics_video_url": "",
    "faces_video_url": "",
    "founded_year": "1882",
    "stadium": "Turf Moor",
    "capacity": "21.944",
    "city": "Burnley",
    "nickname": "Clarets",
    "members": "Desconocido"
  },
  {
    "id": 127,
    "name": "Cagliari",
    "league_id": 4,
    "logo": "img/equipos/Cagliari Calcio.png",
    "slug": "cagliari",
    "sofifa_url": "https://sofifa.com/squad/2373703",
    "tactics_video_url": "",
    "faces_video_url": "",
    "founded_year": "1920",
    "stadium": "Sardegna Arena",
    "capacity": "16.416",
    "city": "Cagliari",
    "nickname": "Gli Isolani",
    "members": "Desconocido"
  },
  {
    "id": 122,
    "name": "Carabobo F.C.",
    "league_id": 16,
    "logo": "img/equipos/Carabobo FC.png",
    "slug": "carabobo-fc",
    "sofifa_url": "",
    "tactics_video_url": "",
    "faces_video_url": "",
    "founded_year": "1997",
    "stadium": "Polideportivo Misael Delgado",
    "capacity": "10.400",
    "city": "Valencia",
    "nickname": "Granates",
    "members": "Desconocido"
  },
  {
    "id": 83,
    "name": "Ceará",
    "league_id": 7,
    "logo": "img/equipos/Ceará.png",
    "slug": "ceara",
    "sofifa_url": "https://sofifa.com/squad/2306905",
    "tactics_video_url": "",
    "faces_video_url": "",
    "founded_year": "1914",
    "stadium": "Arena Castelão",
    "capacity": "63.903",
    "city": "Fortaleza",
    "nickname": "Vozão",
    "members": "Desconocido"
  },
  {
    "id": 62,
    "name": "Celta",
    "league_id": 5,
    "logo": "img/equipos/R.C. Celta de Vigo.png",
    "slug": "rcd-celta-de-vigo",
    "sofifa_url": "https://sofifa.com/squad/2292501",
    "tactics_video_url": "",
    "faces_video_url": "",
    "founded_year": "1923",
    "stadium": "Abanca Balaídos",
    "capacity": "29.000",
    "city": "Vigo",
    "nickname": "Os Celestes",
    "members": "Desconocido"
  },
  {
    "id": 10,
    "name": "Central Córdoba (SdE)",
    "league_id": 1,
    "logo": "img/equipos/Club Atletico Central Cordoba.png",
    "slug": "central-cordoba-sde",
    "sofifa_url": "https://sofifa.com/squad/2212798",
    "tactics_video_url": "",
    "faces_video_url": "",
    "founded_year": "1919",
    "stadium": "Alfredo Terrera",
    "capacity": "21.500",
    "city": "Santiago del Estero",
    "nickname": "Ferroviario",
    "members": "33.155"
  },
  {
    "id": 113,
    "name": "Cerro Porteño",
    "league_id": 13,
    "logo": "img/equipos/Cerro Porteño.png",
    "slug": "cerro-porteno",
    "sofifa_url": "",
    "tactics_video_url": "",
    "faces_video_url": "",
    "founded_year": "1912",
    "stadium": "Estadio General Pablo Rojas",
    "capacity": "45.000",
    "city": "Asunción",
    "nickname": "El Ciclón",
    "members": "Desconocido"
  },
  {
    "id": 37,
    "name": "Chelsea",
    "league_id": 2,
    "logo": "img/equipos/Chelsea.png",
    "slug": "chelsea",
    "sofifa_url": "https://sofifa.com/squad/2224390",
    "tactics_video_url": "",
    "faces_video_url": "",
    "founded_year": "1905",
    "stadium": "Stamford Bridge",
    "capacity": "40.343",
    "city": "Londres",
    "nickname": "Blues",
    "members": "Desconocido"
  },
  {
    "id": 100,
    "name": "Colo Colo",
    "league_id": 8,
    "logo": "img/equipos/Colo Colo.png",
    "slug": "colo-colo",
    "sofifa_url": "https://sofifa.com/squad/2237546",
    "tactics_video_url": "",
    "faces_video_url": "",
    "founded_year": "1925",
    "stadium": "Estadio Monumental",
    "capacity": "47.347",
    "city": "Santiago",
    "nickname": "Cacique",
    "members": "58.500"
  },
  {
    "id": 128,
    "name": "Como",
    "league_id": 4,
    "logo": "img/equipos/Como 1907.png",
    "slug": "como",
    "sofifa_url": "https://sofifa.com/squad/2373718",
    "tactics_video_url": "",
    "faces_video_url": "",
    "founded_year": "1907",
    "stadium": "Giuseppe Sinigaglia",
    "capacity": "12.039",
    "city": "Como",
    "nickname": "Lariani",
    "members": "Desconocido"
  },
  {
    "id": 84,
    "name": "Corinthians",
    "league_id": 7,
    "logo": "img/equipos/Corinthians.png",
    "slug": "corinthians",
    "sofifa_url": "https://sofifa.com/squad/2305953",
    "tactics_video_url": "",
    "faces_video_url": "",
    "founded_year": "1910",
    "stadium": "Neo Química Arena",
    "capacity": "47.605",
    "city": "São Paulo",
    "nickname": "Timão",
    "members": "Desconocido"
  },
  {
    "id": 129,
    "name": "Cremonese",
    "league_id": 4,
    "logo": "img/equipos/US Cremonese.png",
    "slug": "cremonese",
    "sofifa_url": "https://sofifa.com/squad/2373763",
    "tactics_video_url": "",
    "faces_video_url": "",
    "founded_year": "1903",
    "stadium": "Giovanni Zini",
    "capacity": "16.003",
    "city": "Cremona",
    "nickname": "I Grigiorossi",
    "members": "Desconocido"
  },
  {
    "id": 85,
    "name": "Cruzeiro",
    "league_id": 7,
    "logo": "img/equipos/Cruzeiro.png",
    "slug": "cruzeiro",
    "sofifa_url": "https://sofifa.com/squad/2305949",
    "tactics_video_url": "",
    "faces_video_url": "",
    "founded_year": "1921",
    "stadium": "Mineirão",
    "capacity": "61.927",
    "city": "Belo Horizonte",
    "nickname": "Raposa",
    "members": "95.000 (sep 2025)"
  },
  {
    "id": 38,
    "name": "Crystal Palace",
    "league_id": 2,
    "logo": "img/equipos/Crystal Palace.png",
    "slug": "crystal-palace",
    "sofifa_url": "https://sofifa.com/squad/2271230",
    "tactics_video_url": "",
    "faces_video_url": "",
    "founded_year": "1905",
    "stadium": "Selhurst Park",
    "capacity": "25.486",
    "city": "Londres",
    "nickname": "Eagles",
    "members": "Desconocido"
  },
  {
    "id": 22,
    "name": "Defensa y Justicia",
    "league_id": 1,
    "logo": "img/equipos/Club Social y Deportivo Defensa y Justicia.png",
    "slug": "defensa-y-justicia",
    "sofifa_url": "https://sofifa.com/squad/2213233",
    "tactics_video_url": "",
    "faces_video_url": "",
    "founded_year": "1935",
    "stadium": "Norberto Tomaghello",
    "capacity": "20.000",
    "city": "Buenos Aires",
    "nickname": "Halcón",
    "members": "12.000"
  },
  {
    "id": 23,
    "name": "Deportivo Riestra",
    "league_id": 1,
    "logo": "img/equipos/Club Deportivo Riestra.png",
    "slug": "deportivo-riestra",
    "sofifa_url": "https://sofifa.com/squad/2211292",
    "tactics_video_url": "",
    "faces_video_url": "",
    "founded_year": "1931",
    "stadium": "Guillermo Laza",
    "capacity": "3.000",
    "city": "Buenos Aires",
    "nickname": "Blanquinegro",
    "members": "1.000"
  },
  {
    "id": 123,
    "name": "Deportivo Táchira",
    "league_id": 16,
    "logo": "img/equipos/Deportivo Tachira.png",
    "slug": "deportivo-tachira",
    "sofifa_url": "",
    "tactics_video_url": "",
    "faces_video_url": "",
    "founded_year": "1974",
    "stadium": "Estadio Pueblo Nuevo",
    "capacity": "38.755",
    "city": "San Cristóbal",
    "nickname": "Aurinegros",
    "members": "Desconocido"
  },
  {
    "id": 63,
    "name": "Elche",
    "league_id": 5,
    "logo": "img/equipos/Elche C.F..png",
    "slug": "elche-cf",
    "sofifa_url": "https://sofifa.com/squad/2294420",
    "tactics_video_url": "",
    "faces_video_url": "",
    "founded_year": "1923",
    "stadium": "Manuel Martínez Valero",
    "capacity": "33.732",
    "city": "Elche",
    "nickname": "Franjiverdes",
    "members": "Desconocido"
  },
  {
    "id": 64,
    "name": "Espanyol",
    "league_id": 5,
    "logo": "img/equipos/R.C.D. Espanyol.png",
    "slug": "rcd-espanyol",
    "sofifa_url": "https://sofifa.com/squad/2302728",
    "tactics_video_url": "",
    "faces_video_url": "",
    "founded_year": "1900",
    "stadium": "Stage Front Stadium",
    "capacity": "40.000",
    "city": "Barcelona",
    "nickname": "Pericos",
    "members": "Desconocido"
  },
  {
    "id": 27,
    "name": "Estudiantes (LP)",
    "league_id": 1,
    "logo": "img/equipos/Club Estudiantes de La Plata.png",
    "slug": "estudiantes-lp",
    "sofifa_url": "https://sofifa.com/squad/2211227",
    "tactics_video_url": "",
    "faces_video_url": "",
    "founded_year": "1905",
    "stadium": "Jorge Luis Hirschi",
    "capacity": "30.000",
    "city": "Buenos Aires",
    "nickname": "Pincha",
    "members": "60.000"
  },
  {
    "id": 39,
    "name": "Everton",
    "league_id": 2,
    "logo": "img/equipos/Everton.png",
    "slug": "everton",
    "sofifa_url": "https://sofifa.com/squad/2271542",
    "tactics_video_url": "",
    "faces_video_url": "",
    "founded_year": "1878",
    "stadium": "Hill Dickinson Stadium (a partir de 2025/26)",
    "capacity": "~53.000 (aproximado)",
    "city": "Liverpool",
    "nickname": "Toffees",
    "members": "Desconocido"
  },
  {
    "id": 130,
    "name": "Fiorentina",
    "league_id": 4,
    "logo": "img/equipos/Fiorentina.png",
    "slug": "fiorentina",
    "sofifa_url": "https://sofifa.com/squad/2373803",
    "tactics_video_url": "",
    "faces_video_url": "",
    "founded_year": "1926",
    "stadium": "Artemio Franchi",
    "capacity": "43.147",
    "city": "Florencia",
    "nickname": "La Viola",
    "members": "Desconocido"
  },
  {
    "id": 86,
    "name": "Flamengo",
    "league_id": 7,
    "logo": "img/equipos/Flamengo.png",
    "slug": "flamengo",
    "sofifa_url": "https://sofifa.com/squad/2305912",
    "tactics_video_url": "",
    "faces_video_url": "",
    "founded_year": "1895",
    "stadium": "Maracanã",
    "capacity": "78.838",
    "city": "Río de Janeiro",
    "nickname": "Mengão",
    "members": "Desconocido"
  },
  {
    "id": 87,
    "name": "Fluminense",
    "league_id": 7,
    "logo": "img/equipos/Fluminense.png",
    "slug": "fluminense",
    "sofifa_url": "https://sofifa.com/squad/2305903",
    "tactics_video_url": "",
    "faces_video_url": "",
    "founded_year": "1902",
    "stadium": "Maracanã",
    "capacity": "78.838",
    "city": "Río de Janeiro",
    "nickname": "Tricolor",
    "members": "Desconocido"
  },
  {
    "id": 88,
    "name": "Fortaleza",
    "league_id": 7,
    "logo": "img/equipos/Fortaleza.png",
    "slug": "fortaleza",
    "sofifa_url": "https://sofifa.com/squad/2305899",
    "tactics_video_url": "",
    "faces_video_url": "",
    "founded_year": "1918",
    "stadium": "Arena Castelão",
    "capacity": "63.903",
    "city": "Fortaleza",
    "nickname": "Leão",
    "members": "Desconocido"
  },
  {
    "id": 40,
    "name": "Fulham",
    "league_id": 2,
    "logo": "img/equipos/Fulham.png",
    "slug": "fulham",
    "sofifa_url": "https://sofifa.com/squad/2271749",
    "tactics_video_url": "",
    "faces_video_url": "",
    "founded_year": "1879",
    "stadium": "Craven Cottage",
    "capacity": "24.500",
    "city": "Londres",
    "nickname": "Cottagers",
    "members": "Desconocido"
  },
  {
    "id": 65,
    "name": "Getafe",
    "league_id": 5,
    "logo": "img/equipos/Getafe C.F..png",
    "slug": "getafe-cf",
    "sofifa_url": "https://sofifa.com/squad/2304601",
    "tactics_video_url": "",
    "faces_video_url": "",
    "founded_year": "1983",
    "stadium": "Coliseum",
    "capacity": "17.000",
    "city": "Getafe",
    "nickname": "Azulones",
    "members": "Desconocido"
  },
  {
    "id": 11,
    "name": "Gimnasia (LP)",
    "league_id": 1,
    "logo": "img/equipos/Club de Gimnasia y Esgrima La Plata.png",
    "slug": "gimnasia-lp",
    "sofifa_url": "https://sofifa.com/squad/2212486",
    "tactics_video_url": "",
    "faces_video_url": "",
    "founded_year": "1887",
    "stadium": "Juan Carmelo Zerillo",
    "capacity": "31.461",
    "city": "Buenos Aires",
    "nickname": "Lobo",
    "members": "55.437"
  },
  {
    "id": 66,
    "name": "Girona",
    "league_id": 5,
    "logo": "img/equipos/Girona F.C..png",
    "slug": "girona-fc",
    "sofifa_url": "https://sofifa.com/squad/2304903",
    "tactics_video_url": "",
    "faces_video_url": "",
    "founded_year": "1930",
    "stadium": "Montilivi",
    "capacity": "14.624",
    "city": "Gerona",
    "nickname": "Blanquivermells",
    "members": "Desconocido"
  },
  {
    "id": 12,
    "name": "Godoy Cruz",
    "league_id": 1,
    "logo": "img/equipos/Godoy Cruz.png",
    "slug": "godoy-cruz",
    "sofifa_url": "https://sofifa.com/squad/2213570",
    "tactics_video_url": "",
    "faces_video_url": "",
    "founded_year": "1921",
    "stadium": "Malvinas Argentinas",
    "capacity": "42.000",
    "city": "Mendoza",
    "nickname": "Tomba",
    "members": "35.000"
  },
  {
    "id": 89,
    "name": "Grêmio",
    "league_id": 7,
    "logo": "img/equipos/Grêmio.png",
    "slug": "gremio",
    "sofifa_url": "https://sofifa.com/squad/2305893",
    "tactics_video_url": "",
    "faces_video_url": "",
    "founded_year": "1903",
    "stadium": "Arena do Grêmio",
    "capacity": "55.662",
    "city": "Porto Alegre",
    "nickname": "Tricolor Gaúcho",
    "members": "Desconocido"
  },
  {
    "id": 131,
    "name": "Génova",
    "league_id": 4,
    "logo": "img/equipos/Genoa CFC.png",
    "slug": "genova",
    "sofifa_url": "https://sofifa.com/squad/2374413",
    "tactics_video_url": "",
    "faces_video_url": "",
    "founded_year": "1893",
    "stadium": "Luigi Ferraris",
    "capacity": "36.685",
    "city": "Génova",
    "nickname": "Il Grifone",
    "members": "Desconocido"
  },
  {
    "id": 132,
    "name": "Hellas Verona",
    "league_id": 4,
    "logo": "img/equipos/Hellas Verona FC.png",
    "slug": "hellas-verona",
    "sofifa_url": "https://sofifa.com/squad/2374426",
    "tactics_video_url": "",
    "faces_video_url": "",
    "founded_year": "1903",
    "stadium": "Marcantonio Bentegodi",
    "capacity": "31.045",
    "city": "Verona",
    "nickname": "I Gialloblu",
    "members": "Desconocido"
  },
  {
    "id": 13,
    "name": "Huracán",
    "league_id": 1,
    "logo": "img/equipos/Club Atletico Huracan.png",
    "slug": "huracan",
    "sofifa_url": "https://sofifa.com/squad/2211965",
    "tactics_video_url": "",
    "faces_video_url": "",
    "founded_year": "1908",
    "stadium": "Tomás Adolfo Ducó",
    "capacity": "48.314",
    "city": "Buenos Aires",
    "nickname": "Globo",
    "members": "42.000"
  },
  {
    "id": 4,
    "name": "Independiente",
    "league_id": 1,
    "logo": "img/equipos/CAI.png",
    "slug": "independiente",
    "sofifa_url": "https://sofifa.com/squad/2211176",
    "tactics_video_url": "None",
    "faces_video_url": "None",
    "founded_year": "1905",
    "stadium": "Ricardo Enrique Bochini",
    "capacity": "52.777",
    "city": "Buenos Aires",
    "nickname": "Rojo",
    "members": "160.000"
  },
  {
    "id": 111,
    "name": "Independiente del Valle",
    "league_id": 12,
    "logo": "img/equipos/Independiente del Valle.png",
    "slug": "independiente-del-valle",
    "sofifa_url": "",
    "tactics_video_url": "",
    "faces_video_url": "",
    "founded_year": "1977",
    "stadium": "Estadio Banco Guayaquil",
    "capacity": "12.000",
    "city": "Sangolquí",
    "nickname": "Negriazules",
    "members": "Desconocido"
  },
  {
    "id": 28,
    "name": "Independiente Rivadavia",
    "league_id": 1,
    "logo": "img/equipos/Independiente Rivadavia.png",
    "slug": "independiente-rivadavia",
    "sofifa_url": "https://sofifa.com/squad/2213530",
    "tactics_video_url": "",
    "faces_video_url": "",
    "founded_year": "1913",
    "stadium": "Bautista Gargantini",
    "capacity": "24.000",
    "city": "Mendoza",
    "nickname": "Lepra Mendocina",
    "members": "15.000"
  },
  {
    "id": 14,
    "name": "Instituto",
    "league_id": 1,
    "logo": "img/equipos/Instituto Atletico Central Cordoba.png",
    "slug": "instituto",
    "sofifa_url": "https://sofifa.com/squad/2212768",
    "tactics_video_url": "",
    "faces_video_url": "",
    "founded_year": "1918",
    "stadium": "Juan Domingo Perón",
    "capacity": "32.000",
    "city": "Córdoba",
    "nickname": "Gloria",
    "members": "40.000"
  },
  {
    "id": 52,
    "name": "Inter",
    "league_id": 4,
    "logo": "img/equipos/FC Internazionale.png",
    "slug": "inter",
    "sofifa_url": "https://sofifa.com/squad/2232787",
    "tactics_video_url": "",
    "faces_video_url": "",
    "founded_year": "1908",
    "stadium": "Giuseppe Meazza",
    "capacity": "80.018",
    "city": "Milán",
    "nickname": "I Nerazzurri",
    "members": "Desconocido"
  },
  {
    "id": 102,
    "name": "Inter Miami",
    "league_id": 9,
    "logo": "img/equipos/Inter de Miami CF.png",
    "slug": "inter-miami",
    "sofifa_url": "https://sofifa.com/squad/2223594",
    "tactics_video_url": "",
    "faces_video_url": "",
    "founded_year": "2018",
    "stadium": "Chase Stadium",
    "capacity": "21.550",
    "city": "Fort Lauderdale",
    "nickname": "The Herons",
    "members": "Desconocido"
  },
  {
    "id": 90,
    "name": "Internacional",
    "league_id": 7,
    "logo": "img/equipos/Internacional.png",
    "slug": "internacional",
    "sofifa_url": "https://sofifa.com/squad/2305887",
    "tactics_video_url": "",
    "faces_video_url": "",
    "founded_year": "1909",
    "stadium": "Estádio Beira-Rio",
    "capacity": "50.128",
    "city": "Porto Alegre",
    "nickname": "Colorado",
    "members": "150.000"
  },
  {
    "id": 109,
    "name": "Junior",
    "league_id": 11,
    "logo": "img/equipos/Junior.png",
    "slug": "junior",
    "sofifa_url": "",
    "tactics_video_url": "",
    "faces_video_url": "",
    "founded_year": "1924",
    "stadium": "Estadio Metropolitano Roberto Meléndez",
    "capacity": "49.612",
    "city": "Barranquilla",
    "nickname": "Tiburones",
    "members": "Desconocido"
  },
  {
    "id": 91,
    "name": "Juventude",
    "league_id": 7,
    "logo": "img/equipos/Juventude.png",
    "slug": "juventude",
    "sofifa_url": "https://sofifa.com/squad/2305883",
    "tactics_video_url": "",
    "faces_video_url": "",
    "founded_year": "1913",
    "stadium": "Alfredo Jaconi",
    "capacity": "19.919",
    "city": "Caxias do Sul",
    "nickname": "Papo",
    "members": "Desconocido"
  },
  {
    "id": 53,
    "name": "Juventus",
    "league_id": 4,
    "logo": "img/equipos/Juventus FC.png",
    "slug": "juventus",
    "sofifa_url": "https://sofifa.com/squad/2233382",
    "tactics_video_url": "",
    "faces_video_url": "",
    "founded_year": "1897",
    "stadium": "Allianz Stadium",
    "capacity": "41.507",
    "city": "Turín",
    "nickname": "La Vecchia Signora",
    "members": "Desconocido"
  },
  {
    "id": 15,
    "name": "Lanús",
    "league_id": 1,
    "logo": "img/equipos/CA Lanus.png",
    "slug": "lanus",
    "sofifa_url": "https://sofifa.com/squad/2211922",
    "tactics_video_url": "",
    "faces_video_url": "",
    "founded_year": "1915",
    "stadium": "Ciudad de Lanús",
    "capacity": "47.027",
    "city": "Buenos Aires",
    "nickname": "Granate",
    "members": "38.450"
  },
  {
    "id": 133,
    "name": "Lazio",
    "league_id": 4,
    "logo": "img/equipos/SS Lazio.png",
    "slug": "lazio",
    "sofifa_url": "https://sofifa.com/squad/2374491",
    "tactics_video_url": "",
    "faces_video_url": "",
    "founded_year": "1900",
    "stadium": "Olimpico",
    "capacity": "73.261",
    "city": "Roma",
    "nickname": "I Biancocelesti",
    "members": "Desconocido"
  },
  {
    "id": 112,
    "name": "LDU Quito",
    "league_id": 12,
    "logo": "img/equipos/LDU Quito.png",
    "slug": "ldu-quito",
    "sofifa_url": "",
    "tactics_video_url": "",
    "faces_video_url": "",
    "founded_year": "1930",
    "stadium": "Estadio Rodrigo Paz Delgado",
    "capacity": "41.500",
    "city": "Quito",
    "nickname": "Albos",
    "members": "Desconocido"
  },
  {
    "id": 134,
    "name": "Lecce",
    "league_id": 4,
    "logo": "img/equipos/US Lecce.png",
    "slug": "lecce",
    "sofifa_url": "https://sofifa.com/squad/2374535",
    "tactics_video_url": "",
    "faces_video_url": "",
    "founded_year": "1908",
    "stadium": "Via del Mare",
    "capacity": "33.876",
    "city": "Lecce",
    "nickname": "I Salentini",
    "members": "Desconocido"
  },
  {
    "id": 41,
    "name": "Leeds United",
    "league_id": 2,
    "logo": "img/equipos/Leeds United.png",
    "slug": "leeds-united",
    "sofifa_url": "https://sofifa.com/squad/2271811",
    "tactics_video_url": "",
    "faces_video_url": "",
    "founded_year": "1919",
    "stadium": "Elland Road",
    "capacity": "37.890",
    "city": "Leeds",
    "nickname": "Whites",
    "members": "Desconocido"
  },
  {
    "id": 67,
    "name": "Levante",
    "league_id": 5,
    "logo": "img/equipos/Levante U.D..png",
    "slug": "levante-ud",
    "sofifa_url": "https://sofifa.com/squad/2305689",
    "tactics_video_url": "",
    "faces_video_url": "",
    "founded_year": "1909",
    "stadium": "Estadio Ciudad de Valencia",
    "capacity": "26.354",
    "city": "Valencia",
    "nickname": "Granotas",
    "members": "Desconocido"
  },
  {
    "id": 114,
    "name": "Libertad",
    "league_id": 13,
    "logo": "img/equipos/Libertad.png",
    "slug": "libertad",
    "sofifa_url": "",
    "tactics_video_url": "",
    "faces_video_url": "",
    "founded_year": "1905",
    "stadium": "Estadio Tigo La Huerta",
    "capacity": "10.000",
    "city": "Asunción",
    "nickname": "Gumarelo",
    "members": "Desconocido"
  },
  {
    "id": 42,
    "name": "Liverpool",
    "league_id": 2,
    "logo": "img/equipos/Liverpool.png",
    "slug": "liverpool",
    "sofifa_url": "https://sofifa.com/squad/2218262",
    "tactics_video_url": "",
    "faces_video_url": "",
    "founded_year": "1892",
    "stadium": "Anfield",
    "capacity": "61.276",
    "city": "Liverpool",
    "nickname": "Reds",
    "members": "Desconocido"
  },
  {
    "id": 119,
    "name": "Liverpool FC",
    "league_id": 15,
    "logo": "img/equipos/Liverpool FC Uruguay.png",
    "slug": "liverpool-uru",
    "sofifa_url": "",
    "tactics_video_url": "",
    "faces_video_url": "",
    "founded_year": "1915",
    "stadium": "Estadio Belvedere",
    "capacity": "10.000",
    "city": "Montevideo",
    "nickname": "Negriazules",
    "members": "Desconocido"
  },
  {
    "id": 68,
    "name": "Mallorca",
    "league_id": 5,
    "logo": "img/equipos/R.C.D. Mallorca.png",
    "slug": "rcd-mallorca",
    "sofifa_url": "https://sofifa.com/squad/2305712",
    "tactics_video_url": "",
    "faces_video_url": "",
    "founded_year": "1916",
    "stadium": "Estadi Mallorca Son Moix",
    "capacity": "25.000",
    "city": "Palma",
    "nickname": "Bermellones",
    "members": "Desconocido"
  },
  {
    "id": 43,
    "name": "Manchester City",
    "league_id": 2,
    "logo": "img/equipos/Manchester City.png",
    "slug": "manchester-city",
    "sofifa_url": "https://sofifa.com/squad/2222949",
    "tactics_video_url": "",
    "faces_video_url": "",
    "founded_year": "1880",
    "stadium": "Etihad Stadium",
    "capacity": "53.400",
    "city": "Mánchester",
    "nickname": "Citizens",
    "members": "Desconocido"
  },
  {
    "id": 44,
    "name": "Manchester United",
    "league_id": 2,
    "logo": "img/equipos/Manchester United.png",
    "slug": "manchester-united",
    "sofifa_url": "https://sofifa.com/squad/2226122",
    "tactics_video_url": "",
    "faces_video_url": "",
    "founded_year": "1878",
    "stadium": "Old Trafford",
    "capacity": "74.310",
    "city": "Mánchester",
    "nickname": "Red Devils",
    "members": "Desconocido"
  },
  {
    "id": 54,
    "name": "Milan",
    "league_id": 4,
    "logo": "img/equipos/AC Milan.png",
    "slug": "milan",
    "sofifa_url": "https://sofifa.com/squad/2233344",
    "tactics_video_url": "",
    "faces_video_url": "",
    "founded_year": "1899",
    "stadium": "Giuseppe Meazza",
    "capacity": "80.018",
    "city": "Milán",
    "nickname": "I Rossoneri",
    "members": "Desconocido"
  },
  {
    "id": 108,
    "name": "Millonarios",
    "league_id": 11,
    "logo": "img/equipos/Millonarios.png",
    "slug": "millonarios",
    "sofifa_url": "",
    "tactics_video_url": "",
    "faces_video_url": "",
    "founded_year": "1946",
    "stadium": "Estadio Nemesio Camacho El Campín",
    "capacity": "36.343",
    "city": "Bogotá",
    "nickname": "El Ballet Azul",
    "members": "Desconocido"
  },
  {
    "id": 92,
    "name": "Mirassol",
    "league_id": 7,
    "logo": "img/equipos/Mirassol.png",
    "slug": "mirassol",
    "sofifa_url": "https://sofifa.com/squad/2305870",
    "tactics_video_url": "",
    "faces_video_url": "",
    "founded_year": "1924",
    "stadium": "Estádio José Maria de Campos Maia",
    "capacity": "15.000",
    "city": "Mirassol",
    "nickname": "Leão da Araraquarense",
    "members": "Desconocido"
  },
  {
    "id": 120,
    "name": "Nacional",
    "league_id": 15,
    "logo": "img/equipos/Nacional.png",
    "slug": "nacional",
    "sofifa_url": "",
    "tactics_video_url": "",
    "faces_video_url": "",
    "founded_year": "1899",
    "stadium": "Gran Parque Central",
    "capacity": "37.000",
    "city": "Montevideo",
    "nickname": "Bolsilludos",
    "members": "~85.000"
  },
  {
    "id": 55,
    "name": "Napoli",
    "league_id": 4,
    "logo": "img/equipos/Napoli.png",
    "slug": "napoli",
    "sofifa_url": "https://sofifa.com/squad/2232780",
    "tactics_video_url": "",
    "faces_video_url": "",
    "founded_year": "1926",
    "stadium": "Diego Armando Maradona",
    "capacity": "54.726",
    "city": "Nápoles",
    "nickname": "Gli Azzurri",
    "members": "Desconocido"
  },
  {
    "id": 45,
    "name": "Newcastle United",
    "league_id": 2,
    "logo": "img/equipos/Newcastle United.png",
    "slug": "newcastle-united",
    "sofifa_url": "https://sofifa.com/squad/2273082",
    "tactics_video_url": "",
    "faces_video_url": "",
    "founded_year": "1892",
    "stadium": "St James' Park",
    "capacity": "52.305",
    "city": "Newcastle",
    "nickname": "Magpies",
    "members": "Desconocido"
  },
  {
    "id": 6,
    "name": "Newell's Old Boys",
    "league_id": 1,
    "logo": "img/equipos/Club Atletico Newells Old Boys.png",
    "slug": "newells",
    "sofifa_url": "https://sofifa.com/squad/2211273",
    "tactics_video_url": "https://sofifa.com/squad/2211273",
    "faces_video_url": "",
    "founded_year": "1903",
    "stadium": "Marcelo Bielsa",
    "capacity": "42.000",
    "city": "Rosario",
    "nickname": "Lepra",
    "members": "83.040"
  },
  {
    "id": 46,
    "name": "Nottingham Forest",
    "league_id": 2,
    "logo": "img/equipos/Nottingham Forest.png",
    "slug": "nottingham-forest",
    "sofifa_url": "https://sofifa.com/squad/2273090",
    "tactics_video_url": "",
    "faces_video_url": "",
    "founded_year": "1865",
    "stadium": "City Ground",
    "capacity": "30.445",
    "city": "Nottingham",
    "nickname": "Forest",
    "members": "Desconocido"
  },
  {
    "id": 115,
    "name": "Olimpia",
    "league_id": 13,
    "logo": "img/equipos/Olimpia.png",
    "slug": "olimpia",
    "sofifa_url": "",
    "tactics_video_url": "",
    "faces_video_url": "",
    "founded_year": "1902",
    "stadium": "Estadio Manuel Ferreira",
    "capacity": "20.000",
    "city": "Asunción",
    "nickname": "El Decano",
    "members": "Desconocido"
  },
  {
    "id": 69,
    "name": "Osasuna",
    "league_id": 5,
    "logo": "img/equipos/C.A. Osasuna.png",
    "slug": "ca-osasuna",
    "sofifa_url": "https://sofifa.com/squad/2307649",
    "tactics_video_url": "",
    "faces_video_url": "",
    "founded_year": "1920",
    "stadium": "El Sadar",
    "capacity": "23.516",
    "city": "Pamplona",
    "nickname": "Rojillos",
    "members": "Desconocido"
  },
  {
    "id": 93,
    "name": "Palmeiras",
    "league_id": 7,
    "logo": "img/equipos/Palmeiras.png",
    "slug": "palmeiras",
    "sofifa_url": "https://sofifa.com/squad/2305876",
    "tactics_video_url": "",
    "faces_video_url": "",
    "founded_year": "1914",
    "stadium": "Allianz Parque",
    "capacity": "43.713",
    "city": "São Paulo",
    "nickname": "Verdão",
    "members": "Desconocido"
  },
  {
    "id": 51,
    "name": "Paris Saint-Germain",
    "league_id": 3,
    "logo": "img/equipos/Paris Saint Germain.png",
    "slug": "paris-saint-germain",
    "sofifa_url": "https://sofifa.com/squad/2215506",
    "tactics_video_url": "https://youtu.be/xRbSOiYRTOU?si=AOqcl1e84GBiNyoo",
    "faces_video_url": "",
    "founded_year": "1970",
    "stadium": "Parc des Princes",
    "capacity": "47,929",
    "city": "Paris",
    "nickname": "Les Parisiens",
    "members": "Desconocido"
  },
  {
    "id": 135,
    "name": "Parma",
    "league_id": 4,
    "logo": "img/equipos/Parma Calcio 1913.png",
    "slug": "parma",
    "sofifa_url": "https://sofifa.com/squad/2374564",
    "tactics_video_url": "",
    "faces_video_url": "",
    "founded_year": "1913",
    "stadium": "Ennio Tardini",
    "capacity": "22.350",
    "city": "Parma",
    "nickname": "I Crociati",
    "members": "Desconocido"
  },
  {
    "id": 121,
    "name": "Peñarol",
    "league_id": 15,
    "logo": "img/equipos/Penarol.png",
    "slug": "penarol",
    "sofifa_url": "",
    "tactics_video_url": "",
    "faces_video_url": "",
    "founded_year": "1891",
    "stadium": "Estadio Campeón del Siglo",
    "capacity": "40.000",
    "city": "Montevideo",
    "nickname": "Carboneros",
    "members": "Desconocido"
  },
  {
    "id": 136,
    "name": "Pisa",
    "league_id": 4,
    "logo": "img/equipos/Pisa Sporting Club.png",
    "slug": "pisa",
    "sofifa_url": "https://sofifa.com/squad/2375299",
    "tactics_video_url": "",
    "faces_video_url": "",
    "founded_year": "1909",
    "stadium": "Arena Garibaldi",
    "capacity": "12.508",
    "city": "Pisa",
    "nickname": "Nerazzurri",
    "members": "Desconocido"
  },
  {
    "id": 24,
    "name": "Platense",
    "league_id": 1,
    "logo": "img/equipos/Club Atletico Platense.png",
    "slug": "platense",
    "sofifa_url": "https://sofifa.com/squad/2211900",
    "tactics_video_url": "",
    "faces_video_url": "",
    "founded_year": "1905",
    "stadium": "Ciudad de Vicente López",
    "capacity": "28.320",
    "city": "Buenos Aires",
    "nickname": "Calamar",
    "members": "15.000"
  },
  {
    "id": 3,
    "name": "Racing Club",
    "league_id": 1,
    "logo": "img/equipos/Racing Club.png",
    "slug": "racing-club",
    "sofifa_url": "https://sofifa.com/squad/2211138",
    "tactics_video_url": "None",
    "faces_video_url": "None",
    "founded_year": "1903",
    "stadium": "Presidente PerónNone",
    "capacity": "50.880",
    "city": "Buenos Aires",
    "nickname": "Academia",
    "members": "103.422"
  },
  {
    "id": 72,
    "name": "Rayo Vallecano",
    "league_id": 5,
    "logo": "img/equipos/Rayo Vallecano.png",
    "slug": "rayo-vallecano",
    "sofifa_url": "https://sofifa.com/squad/2307662",
    "tactics_video_url": "",
    "faces_video_url": "",
    "founded_year": "1924",
    "stadium": "Estadio de Vallecas",
    "capacity": "14.505",
    "city": "Madrid",
    "nickname": "Franjirrojos",
    "members": "Desconocido"
  },
  {
    "id": 61,
    "name": "Real Betis",
    "league_id": 5,
    "logo": "img/equipos/Real Betis.png",
    "slug": "real-betis",
    "sofifa_url": "https://sofifa.com/squad/2310037",
    "tactics_video_url": "",
    "faces_video_url": "",
    "founded_year": "1907",
    "stadium": "Benito Villamarín",
    "capacity": "60.721",
    "city": "Sevilla",
    "nickname": "Los Verdiblancos",
    "members": "Desconocido"
  },
  {
    "id": 70,
    "name": "Real Madrid",
    "league_id": 5,
    "logo": "img/equipos/Real Madrid C.F..png",
    "slug": "real-madrid-cf",
    "sofifa_url": "https://sofifa.com/squad/2215516",
    "tactics_video_url": "https://youtu.be/7Rso35sZH00?si=LFuf029OmtjJyus2",
    "faces_video_url": "",
    "founded_year": "1902",
    "stadium": "Santiago Bernabéu",
    "capacity": "81.044",
    "city": "Madrid",
    "nickname": "Los Merengues",
    "members": "Desconocido"
  },
  {
    "id": 71,
    "name": "Real Oviedo",
    "league_id": 5,
    "logo": "img/equipos/Real Oviedo.png",
    "slug": "real-oviedo",
    "sofifa_url": "https://sofifa.com/squad/2310170",
    "tactics_video_url": "",
    "faces_video_url": "",
    "founded_year": "1926",
    "stadium": "Estadio Carlos Tartiere",
    "capacity": "30.500",
    "city": "Oviedo",
    "nickname": "Carbayones",
    "members": "Desconocido"
  },
  {
    "id": 73,
    "name": "Real Sociedad",
    "league_id": 5,
    "logo": "img/equipos/Real Sociedad.png",
    "slug": "real-sociedad",
    "sofifa_url": "https://sofifa.com/squad/2310183",
    "tactics_video_url": "",
    "faces_video_url": "",
    "founded_year": "1909",
    "stadium": "Reale Arena",
    "capacity": "40.000",
    "city": "San Sebastián",
    "nickname": "Txuri-urdin",
    "members": "Desconocido"
  },
  {
    "id": 94,
    "name": "Red Bull Bragantino",
    "league_id": 7,
    "logo": "img/equipos/Red Bull Bragantino.png",
    "slug": "red-bull-bragantino",
    "sofifa_url": "https://sofifa.com/squad/2306911",
    "tactics_video_url": "",
    "faces_video_url": "",
    "founded_year": "1928",
    "stadium": "Estádio Nabi Abi Chedid",
    "capacity": "15.010",
    "city": "Bragança Paulista",
    "nickname": "Massa Bruta",
    "members": "Desconocido"
  },
  {
    "id": 1,
    "name": "River Plate",
    "league_id": 1,
    "logo": "img/equipos/Club Atletico River Plate.png",
    "slug": "river-plate",
    "sofifa_url": "https://sofifa.com/squad/2211113",
    "tactics_video_url": "https://youtu.be/ZBX-seRUDIc?si=vbZ4qePfJtbLZHR4",
    "faces_video_url": "https://youtu.be/wLT5QafPckc?si=VZUv0S4o1feYazeG",
    "founded_year": "1901",
    "stadium": "Mâs Monumental",
    "capacity": "84.567",
    "city": "Buenos Aires",
    "nickname": "Millonario",
    "members": "351.487"
  },
  {
    "id": 56,
    "name": "Roma",
    "league_id": 4,
    "logo": "img/equipos/AS Roma.png",
    "slug": "roma",
    "sofifa_url": "https://sofifa.com/squad/2233455",
    "tactics_video_url": "",
    "faces_video_url": "",
    "founded_year": "1927",
    "stadium": "Stadio Olimpico",
    "capacity": "70.634",
    "city": "Roma",
    "nickname": "I Giallorossi",
    "members": "Desconocido"
  },
  {
    "id": 16,
    "name": "Rosario Central",
    "league_id": 1,
    "logo": "img/equipos/Club Atletico Rosario Central.png",
    "slug": "rosario-central",
    "sofifa_url": "https://sofifa.com/squad/2211259",
    "tactics_video_url": "",
    "faces_video_url": "",
    "founded_year": "1889",
    "stadium": "Gigante de Arroyito",
    "capacity": "41.654",
    "city": "Rosario",
    "nickname": "Canalla",
    "members": "96.297"
  },
  {
    "id": 104,
    "name": "San Antonio Bulo Bulo",
    "league_id": 10,
    "logo": "img/equipos/San Antonio Bulo Bulo.png",
    "slug": "san-antonio-bulo-bulo",
    "sofifa_url": "https://sofifa.com/squad/2242020",
    "tactics_video_url": "",
    "faces_video_url": "",
    "founded_year": "1960",
    "stadium": "Estadio Carlos Villegas",
    "capacity": "17.000",
    "city": "Bulo Bulo",
    "nickname": "Desconocido",
    "members": "Desconocido"
  },
  {
    "id": 5,
    "name": "San Lorenzo",
    "league_id": 1,
    "logo": "img/equipos/CA San Lorenzo de Almagro.png",
    "slug": "san-lorenzo",
    "sofifa_url": "https://sofifa.com/squad/2211217",
    "tactics_video_url": "None",
    "faces_video_url": "None",
    "founded_year": "1908",
    "stadium": "Pedro Bidegain",
    "capacity": "47.964",
    "city": "Buenos Aires",
    "nickname": "Ciclón",
    "members": "89.717"
  },
  {
    "id": 30,
    "name": "San Martín (SJ)",
    "league_id": 1,
    "logo": "img/equipos/Club Atlético San Martín.png",
    "slug": "san-martin-sj",
    "sofifa_url": "https://sofifa.com/squad/2217307",
    "tactics_video_url": "",
    "faces_video_url": "",
    "founded_year": "1907",
    "stadium": "Ingeniero Hilario Sánchez",
    "capacity": "25.250",
    "city": "San Juan",
    "nickname": "Verdinegro",
    "members": "15.000"
  },
  {
    "id": 95,
    "name": "Santos",
    "league_id": 7,
    "logo": "img/equipos/Santos.png",
    "slug": "santos",
    "sofifa_url": "https://sofifa.com/squad/2305861",
    "tactics_video_url": "",
    "faces_video_url": "",
    "founded_year": "1912",
    "stadium": "Vila Belmiro",
    "capacity": "16.068",
    "city": "Santos",
    "nickname": "Peixe",
    "members": "Desconocido"
  },
  {
    "id": 17,
    "name": "Sarmiento",
    "league_id": 1,
    "logo": "img/equipos/Sarmiento de Junin.png",
    "slug": "sarmiento",
    "sofifa_url": "https://sofifa.com/squad/2214179",
    "tactics_video_url": "",
    "faces_video_url": "",
    "founded_year": "1911",
    "stadium": "Eva Perón",
    "capacity": "22.000",
    "city": "Buenos Aires",
    "nickname": "Verde",
    "members": "10.000"
  },
  {
    "id": 137,
    "name": "Sassuolo",
    "league_id": 4,
    "logo": "img/equipos/US Sassuolo.png",
    "slug": "sassuolo",
    "sofifa_url": "https://sofifa.com/squad/2375308",
    "tactics_video_url": "",
    "faces_video_url": "",
    "founded_year": "1920",
    "stadium": "MAPEI Stadium",
    "capacity": "21.584",
    "city": "Sassuolo",
    "nickname": "I Neroverdi",
    "members": "Desconocido"
  },
  {
    "id": 74,
    "name": "Sevilla",
    "league_id": 5,
    "logo": "img/equipos/Sevilla F.C..png",
    "slug": "sevilla-fc",
    "sofifa_url": "https://sofifa.com/squad/2310285",
    "tactics_video_url": "",
    "faces_video_url": "",
    "founded_year": "1890",
    "stadium": "Ramón Sánchez Pizjuán",
    "capacity": "43.833",
    "city": "Sevilla",
    "nickname": "Hispalenses",
    "members": "Desconocido"
  },
  {
    "id": 96,
    "name": "Sport Recife",
    "league_id": 7,
    "logo": "img/equipos/Sport.png",
    "slug": "sport",
    "sofifa_url": "https://sofifa.com/squad/2258978",
    "tactics_video_url": "",
    "faces_video_url": "",
    "founded_year": "1905",
    "stadium": "Ilha do Retiro",
    "capacity": "32.983",
    "city": "Recife",
    "nickname": "Leão",
    "members": "Desconocido"
  },
  {
    "id": 117,
    "name": "Sporting Cristal",
    "league_id": 14,
    "logo": "img/equipos/Sporting Cristal.png",
    "slug": "sporting-cristal",
    "sofifa_url": "",
    "tactics_video_url": "",
    "faces_video_url": "",
    "founded_year": "1955",
    "stadium": "Estadio Alberto Gallardo",
    "capacity": "18.000",
    "city": "Lima",
    "nickname": "Cerveceros",
    "members": "Desconocido"
  },
  {
    "id": 47,
    "name": "Sunderland",
    "league_id": 2,
    "logo": "img/equipos/Sunderland.png",
    "slug": "sunderland",
    "sofifa_url": "https://sofifa.com/squad/2273115",
    "tactics_video_url": "",
    "faces_video_url": "",
    "founded_year": "1879",
    "stadium": "Stadium of Light",
    "capacity": "49.000",
    "city": "Sunderland",
    "nickname": "Black Cats",
    "members": "Desconocido"
  },
  {
    "id": 97,
    "name": "São Paulo",
    "league_id": 7,
    "logo": "img/equipos/São Paulo.png",
    "slug": "sao-paulo",
    "sofifa_url": "https://sofifa.com/squad/2305858",
    "tactics_video_url": "",
    "faces_video_url": "",
    "founded_year": "1930",
    "stadium": "Morumbi",
    "capacity": "72.039",
    "city": "São Paulo",
    "nickname": "Tricolor Paulista",
    "members": "Desconocido"
  },
  {
    "id": 7,
    "name": "Talleres",
    "league_id": 1,
    "logo": "img/equipos/Club Atlético Talleres.png",
    "slug": "talleres",
    "sofifa_url": "https://sofifa.com/squad/2211241",
    "tactics_video_url": "",
    "faces_video_url": "",
    "founded_year": "1913",
    "stadium": "Mario Alberto Kempes",
    "capacity": "57.000",
    "city": "Córdoba",
    "nickname": "Matador",
    "members": "74.262"
  },
  {
    "id": 25,
    "name": "Tigre",
    "league_id": 1,
    "logo": "img/equipos/Club Atletico Tigre.png",
    "slug": "tigre",
    "sofifa_url": "https://sofifa.com/squad/2213585",
    "tactics_video_url": "",
    "faces_video_url": "",
    "founded_year": "1902",
    "stadium": "José Dellagiovanna",
    "capacity": "26.282",
    "city": "Buenos Aires",
    "nickname": "Matador",
    "members": "20.000"
  },
  {
    "id": 138,
    "name": "Torino",
    "league_id": 4,
    "logo": "img/equipos/Torino FC.png",
    "slug": "torino",
    "sofifa_url": "https://sofifa.com/squad/2375319",
    "tactics_video_url": "",
    "faces_video_url": "",
    "founded_year": "1906",
    "stadium": "Olímpico de Turín",
    "capacity": "28.140",
    "city": "Turín",
    "nickname": "Il Toro",
    "members": "Desconocido"
  },
  {
    "id": 48,
    "name": "Tottenham Hotspur",
    "league_id": 2,
    "logo": "img/equipos/Tottenham Hotspur.png",
    "slug": "tottenham-hotspur",
    "sofifa_url": "https://sofifa.com/squad/2226770",
    "tactics_video_url": "",
    "faces_video_url": "",
    "founded_year": "1882",
    "stadium": "Tottenham Hotspur Stadium",
    "capacity": "62.850",
    "city": "Londres",
    "nickname": "Spurs",
    "members": "Desconocido"
  },
  {
    "id": 101,
    "name": "U de Chile",
    "league_id": 8,
    "logo": "img/equipos/UdeChile.png",
    "slug": "u-de-chile",
    "sofifa_url": "https://sofifa.com/squad/2237646",
    "tactics_video_url": "",
    "faces_video_url": "",
    "founded_year": "1927",
    "stadium": "Estadio Nacional Julio Martínez Prádanos",
    "capacity": "48.665",
    "city": "Santiago",
    "nickname": "La U",
    "members": "40.000"
  },
  {
    "id": 139,
    "name": "Udinese",
    "league_id": 4,
    "logo": "img/equipos/Udinese Calcio.png",
    "slug": "udinese",
    "sofifa_url": "https://sofifa.com/squad/2375324",
    "tactics_video_url": "",
    "faces_video_url": "",
    "founded_year": "1896",
    "stadium": "Bluenergy Stadium",
    "capacity": "25.144",
    "city": "Údine",
    "nickname": "I Bianconeri",
    "members": "Desconocido"
  },
  {
    "id": 118,
    "name": "Universitario",
    "league_id": 14,
    "logo": "img/equipos/Universitario.png",
    "slug": "universitario",
    "sofifa_url": "",
    "tactics_video_url": "",
    "faces_video_url": "",
    "founded_year": "1924",
    "stadium": "Estadio Monumental de la U",
    "capacity": "80.000",
    "city": "Lima",
    "nickname": "Cremas",
    "members": "Desconocido"
  },
  {
    "id": 18,
    "name": "Unión",
    "league_id": 1,
    "logo": "img/equipos/Club Atletico Union Santa Fe.png",
    "slug": "union",
    "sofifa_url": "https://sofifa.com/squad/2214213",
    "tactics_video_url": "",
    "faces_video_url": "",
    "founded_year": "1907",
    "stadium": "15 de Abril",
    "capacity": "28.000",
    "city": "Santa Fe",
    "nickname": "Tatengue",
    "members": "26.000"
  },
  {
    "id": 75,
    "name": "Valencia",
    "league_id": 5,
    "logo": "img/equipos/Valencia C.F..png",
    "slug": "valencia-cf",
    "sofifa_url": "https://sofifa.com/squad/2310335",
    "tactics_video_url": "",
    "faces_video_url": "",
    "founded_year": "1919",
    "stadium": "Mestalla",
    "capacity": "48.600",
    "city": "Valencia",
    "nickname": "Che",
    "members": "Desconocido"
  },
  {
    "id": 98,
    "name": "Vasco da Gama",
    "league_id": 7,
    "logo": "img/equipos/Vasco da Gama.png",
    "slug": "vasco-da-gama",
    "sofifa_url": "https://sofifa.com/squad/2305848",
    "tactics_video_url": "",
    "faces_video_url": "",
    "founded_year": "1898",
    "stadium": "São Januário",
    "capacity": "21.860",
    "city": "Río de Janeiro",
    "nickname": "Gigante da Colina",
    "members": "Desconocido"
  },
  {
    "id": 76,
    "name": "Villarreal",
    "league_id": 5,
    "logo": "img/equipos/Villarreal C.F..png",
    "slug": "villarreal-cf",
    "sofifa_url": "https://sofifa.com/squad/2310484",
    "tactics_video_url": "",
    "faces_video_url": "",
    "founded_year": "1923",
    "stadium": "Estadio de la Cerámica",
    "capacity": "23.500",
    "city": "Villarreal",
    "nickname": "El Submarino Amarillo",
    "members": "Desconocido"
  },
  {
    "id": 99,
    "name": "Vitória",
    "league_id": 7,
    "logo": "img/equipos/Vitória.png",
    "slug": "vitoria",
    "sofifa_url": "https://sofifa.com/squad/2305839",
    "tactics_video_url": "",
    "faces_video_url": "",
    "founded_year": "1899",
    "stadium": "Barradão",
    "capacity": "34.535",
    "city": "Salvador",
    "nickname": "Leão da Barra",
    "members": "Desconocido"
  },
  {
    "id": 8,
    "name": "Vélez Sarsfield",
    "league_id": 1,
    "logo": "img/equipos/Velez Sarsfield.png",
    "slug": "velez-sarsfield",
    "sofifa_url": "https://sofifa.com/squad/2211254",
    "tactics_video_url": "",
    "faces_video_url": "",
    "founded_year": "1910",
    "stadium": "José Amalfitani",
    "capacity": "49.540",
    "city": "Buenos Aires",
    "nickname": "Fortín",
    "members": "72.889"
  },
  {
    "id": 49,
    "name": "West Ham United",
    "league_id": 2,
    "logo": "img/equipos/West Ham United.png",
    "slug": "west-ham-united",
    "sofifa_url": "https://sofifa.com/squad/2281076",
    "tactics_video_url": "",
    "faces_video_url": "",
    "founded_year": "1895",
    "stadium": "London Stadium",
    "capacity": "62.500",
    "city": "Londres",
    "nickname": "Hammers",
    "members": "Desconocido"
  },
  {
    "id": 50,
    "name": "Wolverhampton Wanderers",
    "league_id": 2,
    "logo": "img/equipos/Wolverhampton Wanderers.png",
    "slug": "wolverhampton-wanderers",
    "sofifa_url": "https://sofifa.com/squad/2282567",
    "tactics_video_url": "",
    "faces_video_url": "",
    "founded_year": "1877",
    "stadium": "Molineux Stadium",
    "capacity": "32.050",
    "city": "Wolverhampton",
    "nickname": "Wolves",
    "members": "Desconocido"
  }
]